pysqlquery/__init__.py
pysqlquery/constraints/__init__.py
pysqlquery/constraints/base/__init__.py
pysqlquery/constraints/base/constraint.py
pysqlquery/constraints/base/multi_column_named_constraint.py
pysqlquery/constraints/base/named_constraint.py
pysqlquery/constraints/base/single_column_named_constraint.py
pysqlquery/constraints/base/unnamed_constraint.py
pysqlquery/constraints/exceptions/__init__.py
pysqlquery/constraints/exceptions/constraint.py
pysqlquery/constraints/exceptions/multi_column_named_constraint.py
pysqlquery/constraints/exceptions/named_constraint.py
pysqlquery/constraints/exceptions/named_foreign_key.py
pysqlquery/constraints/exceptions/unnamed_constraint.py
pysqlquery/constraints/exceptions/unnamed_foreign_key.py
pysqlquery/constraints/named/__init__.py
pysqlquery/constraints/named/foreign_key.py
pysqlquery/constraints/named/primary_key.py
pysqlquery/constraints/named/unique.py
pysqlquery/constraints/unnamed/__init__.py
pysqlquery/constraints/unnamed/foreign_key.py
pysqlquery/table/__init__.py
pysqlquery/table/column.py
pysqlquery/table/table.py
pysqlquery/table/base/__init__.py
pysqlquery/table/base/table_meta.py
pysqlquery/table/exceptions/__init__.py
pysqlquery/table/exceptions/column.py
pysqlquery/table/exceptions/table.py
pysqlquery/types/__init__.py
pysqlquery/types/bit.py
pysqlquery/types/boolean.py
pysqlquery/types/char.py
pysqlquery/types/date.py
pysqlquery/types/datetime.py
pysqlquery/types/decimal.py
pysqlquery/types/double.py
pysqlquery/types/float.py
pysqlquery/types/integer.py
pysqlquery/types/real.py
pysqlquery/types/string.py
pysqlquery/types/time.py
pysqlquery/types/base/__init__.py
pysqlquery/types/base/sql_date_type.py
pysqlquery/types/base/sql_decimal_type.py
pysqlquery/types/base/sql_int_type.py
pysqlquery/types/base/sql_num_type.py
pysqlquery/types/base/sql_text_type.py
pysqlquery/types/base/sql_type.py
pysqlquery/types/exceptions/__init__.py
pysqlquery/types/exceptions/sql_date_type.py
pysqlquery-1.0.0.dist-info/LICENSE.md
pysqlquery-1.0.0.dist-info/METADATA
pysqlquery-1.0.0.dist-info/WHEEL
pysqlquery-1.0.0.dist-info/top_level.txt
pysqlquery-1.0.0.dist-info/RECORD
